fast_seqfunc/__init__.py
fast_seqfunc/alphabets.py
fast_seqfunc/cli.py
fast_seqfunc/core.py
fast_seqfunc/embedders.py
fast_seqfunc/models.py
fast_seqfunc/preprocessing.py
fast_seqfunc/schemas.py
fast_seqfunc/synthetic.py
fast_seqfunc/utils.py
fast_seqfunc-0.2.0.dist-info/METADATA
fast_seqfunc-0.2.0.dist-info/WHEEL
fast_seqfunc-0.2.0.dist-info/entry_points.txt
fast_seqfunc-0.2.0.dist-info/RECORD
