Metadata-Version: 2.4
Name: fast-seqfunc
Version: 0.2.0
Requires-Python: >=3.10
Requires-Dist: lazy-loader<0.5,>=0.4
Requires-Dist: loguru>=0.7.0
Requires-Dist: numpy>=1.22.0
Requires-Dist: pandas>=1.5.0
Requires-Dist: pycaret<4,>=2.2.3
Requires-Dist: scikit-learn>=1.2.0
Requires-Dist: typer>=0.9.0
